Metadata-Version: 2.1
Name: biokevlar
Version: 0.7
Summary: Reference-free variant discovery scalable to large eukaryotic genomes
Home-page: https://github.com/dib-lab/kevlar
Author: Daniel Standage
Author-email: daniel.standage@gmail.com
License: MIT
Platform: UNKNOWN
Classifier: Development Status :: 4 - Beta
Classifier: Environment :: Console
Classifier: License :: OSI Approved :: MIT License
Classifier: Programming Language :: Python :: 3.5
Classifier: Programming Language :: Python :: 3.6
Classifier: Topic :: Scientific/Engineering :: Bio-Informatics
